[
  {
    "id": "1",
    "word": "Красный",
    "diff": "Easy",
    "cat": "Цвета"
  },
  {
    "id": "2",
    "word": "Синий",
    "diff": "Easy",
    "cat": "Цвета"
  },
  {
    "id": "3",
    "word": "Зеленый",
    "diff": "Easy",
    "cat": "Цвета"
  },
  {
    "id": "4",
    "word": "Желтый",
    "diff": "Easy",
    "cat": "Цвета"
  },
  {
    "id": "5",
    "word": "Розовый",
    "diff": "Easy",
    "cat": "Цвета"
  },
  {
    "id": "6",
    "word": "Серый",
    "diff": "Easy",
    "cat": "Цвета"
  },
  {
    "id": "7",
    "word": "Коричневый",
    "diff": "Easy",
    "cat": "Цвета"
  },
  {
    "id": "8",
    "word": "Белый",
    "diff": "Easy",
    "cat": "Цвета"
  },
  {
    "id": "9",
    "word": "Черный",
    "diff": "Easy",
    "cat": "Цвета"
  },
  {
    "id": "10",
    "word": "Фиолетовый",
    "diff": "Easy",
    "cat": "Цвета"
  },
  {
    "id": "11",
    "word": "Кошка",
    "diff": "Easy",
    "cat": "Животные"
  },
  {
    "id": "12",
    "word": "Собака",
    "diff": "Easy",
    "cat": "Животные"
  },
  {
    "id": "13",
    "word": "Корова",
    "diff": "Easy",
    "cat": "Животные"
  },
  {
    "id": "14",
    "word": "Свинья",
    "diff": "Easy",
    "cat": "Животные"
  },
  {
    "id": "15",
    "word": "Летучая мышь",
    "diff": "Easy",
    "cat": "Животные"
  },
  {
    "id": "16",
    "word": "Крыса",
    "diff": "Easy",
    "cat": "Животные"
  },
  {
    "id": "17",
    "word": "Олень",
    "diff": "Easy",
    "cat": "Животные"
  },
  {
    "id": "18",
    "word": "Лось",
    "diff": "Easy",
    "cat": "Животные"
  },
  {
    "id": "19",
    "word": "Лиса",
    "diff": "Easy",
    "cat": "Животные"
  },
  {
    "id": "20",
    "word": "Кит",
    "diff": "Easy",
    "cat": "Животные"
  },
  {
    "id": "21",
    "word": "Яблоко",
    "diff": "Easy",
    "cat": "Фрукты"
  },
  {
    "id": "22",
    "word": "Манго",
    "diff": "Easy",
    "cat": "Фрукты"
  },
  {
    "id": "23",
    "word": "Киви",
    "diff": "Easy",
    "cat": "Фрукты"
  },
  {
    "id": "24",
    "word": "Банан",
    "diff": "Easy",
    "cat": "Фрукты"
  },
  {
    "id": "25",
    "word": "Груша",
    "diff": "Easy",
    "cat": "Фрукты"
  },
  {
    "id": "26",
    "word": "Апельсин",
    "diff": "Easy",
    "cat": "Фрукты"
  },
  {
    "id": "27",
    "word": "Ананас",
    "diff": "Easy",
    "cat": "Фрукты"
  },
  {
    "id": "28",
    "word": "Виноград",
    "diff": "Easy",
    "cat": "Фрукты"
  },
  {
    "id": "29",
    "word": "Лимон",
    "diff": "Easy",
    "cat": "Фрукты"
  },
  {
    "id": "30",
    "word": "Арбуз",
    "diff": "Easy",
    "cat": "Фрукты"
  },
  {
    "id": "31",
    "word": "Шимпанзе",
    "diff": "Normal",
    "cat": "Животные"
  },
  {
    "id": "32",
    "word": "Бегемот",
    "diff": "Normal",
    "cat": "Животные"
  },
  {
    "id": "33",
    "word": "Кенгуру",
    "diff": "Normal",
    "cat": "Животные"
  },
  {
    "id": "34",
    "word": "Утконос",
    "diff": "Normal",
    "cat": "Животные"
  },
  {
    "id": "35",
    "word": "Аллигатор",
    "diff": "Normal",
    "cat": "Животные"
  },
  {
    "id": "36",
    "word": "Павлин",
    "diff": "Normal",
    "cat": "Животные"
  },
  {
    "id": "37",
    "word": "Страус",
    "diff": "Normal",
    "cat": "Животные"
  },
  {
    "id": "38",
    "word": "Лемур",
    "diff": "Normal",
    "cat": "Животные"
  },
  {
    "id": "39",
    "word": "Броненосец",
    "diff": "Normal",
    "cat": "Животные"
  },
  {
    "id": "40",
    "word": "Енот",
    "diff": "Normal",
    "cat": "Животные"
  },
  {
    "id": "41",
    "word": "Бразилия",
    "diff": "Normal",
    "cat": "Страны"
  },
  {
    "id": "42",
    "word": "Япония",
    "diff": "Normal",
    "cat": "Страны"
  },
  {
    "id": "43",
    "word": "Италия",
    "diff": "Normal",
    "cat": "Страны"
  },
  {
    "id": "44",
    "word": "Россия",
    "diff": "Normal",
    "cat": "Страны"
  },
  {
    "id": "45",
    "word": "Канада",
    "diff": "Normal",
    "cat": "Страны"
  },
  {
    "id": "46",
    "word": "Испания",
    "diff": "Normal",
    "cat": "Страны"
  },
  {
    "id": "47",
    "word": "Франция",
    "diff": "Normal",
    "cat": "Страны"
  },
  {
    "id": "48",
    "word": "Мексика",
    "diff": "Normal",
    "cat": "Страны"
  },
  {
    "id": "49",
    "word": "Индия",
    "diff": "Normal",
    "cat": "Страны"
  },
  {
    "id": "50",
    "word": "Германия",
    "diff": "Normal",
    "cat": "Страны"
  },
  {
    "id": "51",
    "word": "Архитектор",
    "diff": "Normal",
    "cat": "Профессии"
  },
  {
    "id": "52",
    "word": "Инженер",
    "diff": "Normal",
    "cat": "Профессии"
  },
  {
    "id": "53",
    "word": "Доктор",
    "diff": "Normal",
    "cat": "Профессии"
  },
  {
    "id": "54",
    "word": "Юрист",
    "diff": "Normal",
    "cat": "Профессии"
  },
  {
    "id": "55",
    "word": "Бухгалтер",
    "diff": "Normal",
    "cat": "Профессии"
  },
  {
    "id": "56",
    "word": "Учитель",
    "diff": "Normal",
    "cat": "Профессии"
  },
  {
    "id": "57",
    "word": "Повар",
    "diff": "Normal",
    "cat": "Профессии"
  },
  {
    "id": "58",
    "word": "Писатель",
    "diff": "Normal",
    "cat": "Профессии"
  },
  {
    "id": "59",
    "word": "Музыкант",
    "diff": "Normal",
    "cat": "Профессии"
  },
  {
    "id": "60",
    "word": "Ученый",
    "diff": "Normal",
    "cat": "Профессии"
  },
  {
    "id": "61",
    "word": "Хамелеон",
    "diff": "Hard",
    "cat": "Животные"
  },
  {
    "id": "62",
    "word": "Нарвал",
    "diff": "Hard",
    "cat": "Животные"
  },
  {
    "id": "63",
    "word": "Панголин",
    "diff": "Hard",
    "cat": "Животные"
  },
  {
    "id": "64",
    "word": "Окапи",
    "diff": "Hard",
    "cat": "Животные"
  },
  {
    "id": "65",
    "word": "Квокка",
    "diff": "Hard",
    "cat": "Животные"
  },
  {
    "id": "66",
    "word": "Утконос",
    "diff": "Hard",
    "cat": "Животные"
  },
  {
    "id": "67",
    "word": "Капибара",
    "diff": "Hard",
    "cat": "Животные"
  },
  {
    "id": "68",
    "word": "Тапир",
    "diff": "Hard",
    "cat": "Животные"
  },
  {
    "id": "69",
    "word": "Зорилла",
    "diff": "Hard",
    "cat": "Животные"
  },
  {
    "id": "70",
    "word": "Аноа",
    "diff": "Hard",
    "cat": "Животные"
  },
  {
    "id": "71",
    "word": "Ксилофон",
    "diff": "Hard",
    "cat": "Музыкальные инструменты"
  },
  {
    "id": "72",
    "word": "Клавесин",
    "diff": "Hard",
    "cat": "Музыкальные инструменты"
  },
  {
    "id": "73",
    "word": "Терменвокс",
    "diff": "Hard",
    "cat": "Музыкальные инструменты"
  },
  {
    "id": "74",
    "word": "Ситар",
    "diff": "Hard",
    "cat": "Музыкальные инструменты"
  },
  {
    "id": "75",
    "word": "Сузафон",
    "diff": "Hard",
    "cat": "Музыкальные инструменты"
  },
  {
    "id": "76",
    "word": "Челеста",
    "diff": "Hard",
    "cat": "Музыкальные инструменты"
  },
  {
    "id": "77",
    "word": "Саксофон",
    "diff": "Hard",
    "cat": "Музыкальные инструменты"
  },
  {
    "id": "78",
    "word": "Фортепиано",
    "diff": "Hard",
    "cat": "Музыкальные инструменты"
  },
  {
    "id": "79",
    "word": "Клавикорд",
    "diff": "Hard",
    "cat": "Музыкальные инструменты"
  },
  {
    "id": "80",
    "word": "Маримба",
    "diff": "Hard",
    "cat": "Музыкальные инструменты"
  },
  {
    "id": "81",
    "word": "Фотосинтез",
    "diff": "Hard",
    "cat": "Наука"
  },
  {
    "id": "82",
    "word": "Митохондрии",
    "diff": "Hard",
    "cat": "Наука"
  },
  {
    "id": "83",
    "word": "Изотоп",
    "diff": "Hard",
    "cat": "Наука"
  },
  {
    "id": "84",
    "word": "Хромосома",
    "diff": "Hard",
    "cat": "Наука"
  },
  {
    "id": "85",
    "word": "Гомеостаз",
    "diff": "Hard",
    "cat": "Наука"
  },
  {
    "id": "86",
    "word": "Метаболизм",
    "diff": "Hard",
    "cat": "Наука"
  },
  {
    "id": "87",
    "word": "Наночастица",
    "diff": "Hard",
    "cat": "Наука"
  }
]
